{
  "name": "clemens.eth | atweb3",
  "address": "0x9c868c1A597d08C76406E012f6EBf44A42864D75",
  "logoUri": "/logos/delegatees/0x9c868c1A597d08C76406E012f6EBf44A42864D75.jpg",
  "date": "2024-11-05",
  "links": {
    "website": "https://celo.clemens.fi",
    "twitter": "https://x.com/clemensvienna",
    "github": "https://github.com/cleot"
  },
  "interests": [
    "Node Operator",
    "Blockchain Infrastructure",
    "High Availability",
    "Proof-of-Stake"
  ],
  "description": "Blockchain Infrastructure Enthusiast. Node Operator @ atweb3.co"
}
